README.md
setup.cfg
setup.py
PureCloudPlatformClientV2/__init__.py
PureCloudPlatformClientV2/api_client.py
PureCloudPlatformClientV2/configuration.py
PureCloudPlatformClientV2/logger.py
PureCloudPlatformClientV2/purecloud_region_hosts.py
PureCloudPlatformClientV2/rest.py
PureCloudPlatformClientV2/utils.py
PureCloudPlatformClientV2.egg-info/PKG-INFO
PureCloudPlatformClientV2.egg-info/SOURCES.txt
PureCloudPlatformClientV2.egg-info/dependency_links.txt
PureCloudPlatformClientV2.egg-info/requires.txt
PureCloudPlatformClientV2.egg-info/top_level.txt
PureCloudPlatformClientV2/apis/__init__.py
PureCloudPlatformClientV2/apis/alerting_api.py
PureCloudPlatformClientV2/apis/analytics_api.py
PureCloudPlatformClientV2/apis/architect_api.py
PureCloudPlatformClientV2/apis/audit_api.py
PureCloudPlatformClientV2/apis/authorization_api.py
PureCloudPlatformClientV2/apis/billing_api.py
PureCloudPlatformClientV2/apis/chat_api.py
PureCloudPlatformClientV2/apis/coaching_api.py
PureCloudPlatformClientV2/apis/content_management_api.py
PureCloudPlatformClientV2/apis/conversations_api.py
PureCloudPlatformClientV2/apis/data_extensions_api.py
PureCloudPlatformClientV2/apis/external_contacts_api.py
PureCloudPlatformClientV2/apis/fax_api.py
PureCloudPlatformClientV2/apis/flows_api.py
PureCloudPlatformClientV2/apis/gamification_api.py
PureCloudPlatformClientV2/apis/general_data_protection_regulation_api.py
PureCloudPlatformClientV2/apis/geolocation_api.py
PureCloudPlatformClientV2/apis/greetings_api.py
PureCloudPlatformClientV2/apis/groups_api.py
PureCloudPlatformClientV2/apis/identity_provider_api.py
PureCloudPlatformClientV2/apis/integrations_api.py
PureCloudPlatformClientV2/apis/journey_api.py
PureCloudPlatformClientV2/apis/knowledge_api.py
PureCloudPlatformClientV2/apis/language_understanding_api.py
PureCloudPlatformClientV2/apis/languages_api.py
PureCloudPlatformClientV2/apis/learning_api.py
PureCloudPlatformClientV2/apis/license_api.py
PureCloudPlatformClientV2/apis/locations_api.py
PureCloudPlatformClientV2/apis/messaging_api.py
PureCloudPlatformClientV2/apis/mobile_devices_api.py
PureCloudPlatformClientV2/apis/notifications_api.py
PureCloudPlatformClientV2/apis/o_auth_api.py
PureCloudPlatformClientV2/apis/objects_api.py
