Metadata-Version: 2.1
Name: PureCloudPlatformClientV2
Version: 138.0.1
Summary: PureCloud Platform API SDK
Home-page: https://developer.mypurecloud.com/api/rest/client-libraries/python/
Author: Genesys Developer Evangelists
Author-email: DeveloperEvangelists@Genesys.com
License: UNKNOWN
Keywords: Swagger PureCloud Platform API Genesys
Platform: UNKNOWN
